python_sponsorblock/__init__.py
python_sponsorblock/_version.py
python_sponsorblock/constants.py
python_sponsorblock/exceptions.py
python_sponsorblock-0.1.dist-info/METADATA
python_sponsorblock-0.1.dist-info/WHEEL
python_sponsorblock-0.1.dist-info/licenses/LICENSE
python_sponsorblock-0.1.dist-info/RECORD
