Metadata-Version: 2.3
Name: python-sponsorblock
Version: 0.1
Summary: This is a wrapper for the sponsorblock api, enabling you to get the timestamps of sponsor segments from youtube videos.
Author-email: Hazel <hazel_is_cute@proton.me>
License-Expression: MIT
License-File: LICENSE
Classifier: Development Status :: 4 - Beta
Classifier: Intended Audience :: Developers
Classifier: License :: OSI Approved :: MIT License
Classifier: Programming Language :: Python :: 3
Classifier: Programming Language :: Python :: 3.10
Requires-Python: >=3.10
Requires-Dist: requests~=2.31.0
